GojoSTT/__init__.py
Gojo_STT/__init__.py
GojoSST-0.1.dist-info/METADATA
GojoSST-0.1.dist-info/WHEEL
GojoSST-0.1.dist-info/top_level.txt
GojoSST-0.1.dist-info/RECORD
