Metadata-Version: 2.1
Name: GojoSST
Version: 0.1
Summary: This is the first speech to text module ny Gojo Saturo
Author: GojoSaturo-YT
Author-email: samisaturoo@gmail.com
